SpotToBee/SpotToBee.py
SpotToBee/__init__.py
SpotToBee-1.0.5.dist-info/LICENSE
SpotToBee-1.0.5.dist-info/METADATA
SpotToBee-1.0.5.dist-info/WHEEL
SpotToBee-1.0.5.dist-info/entry_points.txt
SpotToBee-1.0.5.dist-info/top_level.txt
SpotToBee-1.0.5.dist-info/RECORD
