Metadata-Version: 2.1
Name: SpotToBee
Version: 1.0.5
Summary: Convert a CSV or Spotify playlist URL to a MusicBee smart playlist
Home-page: https://github.com/BrendanStupik/SpotToBee
Author: Brendan Stupik
Author-email: spottobee@brendanstupik.anonaddy.com
License: MIT
Platform: UNKNOWN
License-File: LICENSE
Requires-Dist: configparser (>=5.0.0)
Requires-Dist: pandas (>=1.0.0)
Requires-Dist: spotipy (>=2.0.0)
